solana_swarm/__init__.py
solana_swarm/main.py
solana_swarm-0.2.2.dist-info/LICENSE
solana_swarm-0.2.2.dist-info/METADATA
solana_swarm-0.2.2.dist-info/WHEEL
solana_swarm-0.2.2.dist-info/entry_points.txt
solana_swarm-0.2.2.dist-info/RECORD
