Metadata-Version: 2.1
Name: solana-swarm
Version: 0.2.2
Summary: Solana AI Agent
Home-page: https://solana-swarm.com
License: MIT
Keywords: ai,agent,ai agent,solana ai agent
Author: Bevan Hunt
Author-email: bevan@bevanhunt.com
Requires-Python: >=3.9,<4.0
Classifier: License :: OSI Approved :: MIT License
Classifier: Operating System :: OS Independent
Classifier: Programming Language :: Python :: 3
Classifier: Programming Language :: Python :: 3.9
Classifier: Programming Language :: Python :: 3.10
Classifier: Programming Language :: Python :: 3.11
Classifier: Programming Language :: Python :: 3.12
Classifier: Programming Language :: Python :: 3.13
Classifier: Programming Language :: Python :: 3 :: Only
Classifier: Topic :: Scientific/Engineering :: Artificial Intelligence
Requires-Dist: click (==8.1.7)
Requires-Dist: cyberchipped (==2.1.6)
Requires-Dist: requests (==2.32.3)
Requires-Dist: solana (==0.35.0)
Requires-Dist: solders (==0.21.0)
Project-URL: Repository, https://github.com/truemagic-coder/solana-swarm
